aldsim/__init__.py
aldsim/aldmodel.py
aldsim/chem.py
aldsim/constants.py
aldsim/solvers.py
aldsim/utils.py
aldsim/core/__init__.py
aldsim/core/diffusion.py
aldsim/core/highar.py
aldsim/core/particle/__init__.py
aldsim/core/particle/fluidizedbed.py
aldsim/core/particle/rotatingdrum.py
aldsim/core/particle/spatialplugflow.py
aldsim/core/particle/spatialwellmixed.py
aldsim/core/softsat/__init__.py
aldsim/core/softsat/batch.py
aldsim/core/softsat/batch/__init__.py
aldsim/core/softsat/batch/plugflow.py
aldsim/core/softsat/batch/wellstirred.py
aldsim/models/__init__.py
aldsim/models/base.py
aldsim/models/batch.py
aldsim/models/spatial.py
aldsim/models/zerod.py
aldsim/reactors/crossflow.py
aldsim-0.0.5.dist-info/licenses/LICENSE
aldsim-0.0.5.dist-info/METADATA
aldsim-0.0.5.dist-info/WHEEL
aldsim-0.0.5.dist-info/top_level.txt
aldsim-0.0.5.dist-info/RECORD
