Metadata-Version: 2.4
Name: aldsim
Version: 0.0.5
Summary: Simple models for atomic layer deposition
Author-email: Angel Yanguas-Gil <angel.yanguas@gmail.com>
Project-URL: Homepage, https://github.com/anglyan/aldsim
Project-URL: Bug Tracker, https://github.com/anglyan/aldsim/issues
Project-URL: Documentation, https://aldsim.readthedocs.io/en/latest/
Keywords: atomic layer deposition,transport models,microelectronics,ALD,atomic scale processing,plasma,thin films
Classifier: Programming Language :: Python :: 3
Classifier: Operating System :: OS Independent
License-File: LICENSE
Requires-Dist: numpy
Requires-Dist: scipy
Requires-Dist: properunits
Provides-Extra: dev
Requires-Dist: pytest; extra == "dev"
Provides-Extra: test
Requires-Dist: pytest; extra == "test"
Dynamic: license-file
